{
  "kind": "collectionType",
  "collectionName": "posts",
  "info": {
    "singularName": "post",
    "pluralName": "posts",
    "displayName": "Blog Posts",
    "description": ""
  },
  "options": {
    "draftAndPublish": true
  },
  "pluginOptions": {},
  "attributes": {
    "title": {
      "type": "string"
    },
    "subtitle": {
      "type": "string"
    },
    "image": {
      "type": "media",
      "multiple": false,
      "required": false,
      "allowedTypes": [
        "images"
      ]
    },
    "content": {
      "type": "blocks"
    },
    "slug": {
      "type": "uid",
      "targetField": "title",
      "required": true
    },
    "author": {
      "type": "enumeration",
      "enum": [
        "Роман Джармухаметов"
      ]
    },
    "category": {
      "type": "enumeration",
      "enum": [
        "Технологии",
        "Бизнес",
        "Продуктивность",
        "Изучение языков"
      ]
    }
  }
}
